inmanta_files/__init__.py
inmanta_files/py.typed
inmanta_plugins/files/__init__.py
inmanta_plugins/files/base.py
inmanta_plugins/files/directory.py
inmanta_plugins/files/host.py
inmanta_plugins/files/json.py
inmanta_plugins/files/setup.cfg
inmanta_plugins/files/symlink.py
inmanta_plugins/files/systemd_unit.py
inmanta_plugins/files/text.py
inmanta_plugins/files/files/.gitkeep
inmanta_plugins/files/model/_init.cf
inmanta_plugins/files/model/host.cf
inmanta_plugins/files/model/json.cf
inmanta_plugins/files/model/systemd_unit.cf
inmanta_plugins/files/templates/.gitkeep
inmanta_plugins/files/templates/systemd_unit.j2
inmanta_module_files-2.6.0.dist-info/METADATA
inmanta_module_files-2.6.0.dist-info/WHEEL
inmanta_module_files-2.6.0.dist-info/top_level.txt
inmanta_module_files-2.6.0.dist-info/RECORD
