Metadata-Version: 2.4
Name: inmanta-module-files
Version: 2.6.0
Summary: Simple module containing various types of resource to manage files.
Author: Guillaume Everarts de Velp
Author-email: edvgui@gmail.com
License: ASL 2.0
Project-URL: Source, https://github.com/edvgui/inmanta-module-files
Project-URL: Changelog, https://github.com/edvgui/inmanta-module-files/blob/master/CHANGELOG.md
Requires-Dist: inmanta-module-std<9
Requires-Dist: inmanta-module-mitogen<1
Requires-Dist: inmanta-core>=15.1.0
Requires-Dist: inmanta-module-files
